{
    /*
     * debug settings
     */
	"sql_logging": false,
	"debug"      : false,

	/*
	 * database settings
	 */
    "propel"     : {
        "datasources" : {
            "gw2spidy" : {
                "adapter" : "mysql",
                "connection" : {
                    "dsn"      : "mysql:host=localhost;dbname=gw2spidy",
                    "user"     : "root",
                    "password" : "root"
                }
            },
            "default" : "gw2spidy"
        },
        "log" : {
            "type"  : "file",
            "name"  : "/var/log/propel/gw2spidy.log",
            "ident" : "propel-gw2spidy",
            "level" : "7"
        },
        "generator_version" : "1.6.7-dev"
    }
}